equation_solver/__init__.py
equation_solver/ai.py
equation_solver/core.py
equation_solver/exceptions.py
equation_solver/server.py
equation_solver/utils.py
equation_solver_ai-1.0.0.dist-info/METADATA
equation_solver_ai-1.0.0.dist-info/WHEEL
equation_solver_ai-1.0.0.dist-info/top_level.txt
equation_solver_ai-1.0.0.dist-info/RECORD
