Metadata-Version: 2.1
Name: equation-solver-ai
Version: 1.0.0
Summary: A solver for univariate polynomial equations (degree 1-4) with AI support
Home-page: https://github.com/John-is-playing/equation-solver
Author: John_MC_Python
Author-email: b297209694@example.com
Classifier: Programming Language :: Python :: 3
Classifier: License :: OSI Approved :: MIT License
Classifier: Operating System :: OS Independent
Requires-Python: >=3.10
Requires-Dist: sympy
Requires-Dist: requests
Requires-Dist: matplotlib
Requires-Dist: pillow
Requires-Dist: psutil
